{
	"name": "Zynga.Payments.StripePlugin",
	"file-filters":
	[
		"Assets/WebGLTemplates/BaseTemplate/js/ZyngaDirectPayDialog.js",
		"Assets/WebGLTemplates/BaseTemplate/js/ZyngaDirectPayDialog.min.js",
		"Assets/Zynga/Payments/IAP/Impl/Plugins/Stripe",
		"-Web/StripePlugin"
	],
	"options":
	[
		{
			"name": "source",
			"_comments": "Includes the source code for the stripe plugin.",
			"file-filters":
			[
				"Web/StripePlugin",
				"-Web/StripePlugin/coverage",
				"-Web/StripePlugin/directpay_locale",
				"-Web/StripePlugin/local.config.json",
				"-Web/StripePlugin/node_modules"
			]
		}
	],
	"metadata":
	{
		"documentation-merger-script":
		[
			"Web/StripePlugin/DocTemplates"
		]
	}
}
